autoremovetorrents/__init__.py
autoremovetorrents/clientstatus.py
autoremovetorrents/conditionlexer.py
autoremovetorrents/conditionparser.py
autoremovetorrents/lextab.py
autoremovetorrents/logger.py
autoremovetorrents/main.py
autoremovetorrents/parsetab.py
autoremovetorrents/strategy.py
autoremovetorrents/task.py
autoremovetorrents/torrent.py
autoremovetorrents/torrentstatus.py
autoremovetorrents/version.py
autoremovetorrents/client/__init__.py
autoremovetorrents/client/deluge.py
autoremovetorrents/client/qbittorrent.py
autoremovetorrents/client/transmission.py
autoremovetorrents/client/utorrent.py
autoremovetorrents/compatibility/__init__.py
autoremovetorrents/compatibility/disk_usage_.py
autoremovetorrents/compatibility/inf_.py
autoremovetorrents/compatibility/open_.py
autoremovetorrents/compatibility/pyyaml_version_.py
autoremovetorrents/compatibility/urlparse_.py
autoremovetorrents/condition/__init__.py
autoremovetorrents/condition/avgdownloadspeed.py
autoremovetorrents/condition/avguploadspeed.py
autoremovetorrents/condition/base.py
autoremovetorrents/condition/connectedleecher.py
autoremovetorrents/condition/connectedseeder.py
autoremovetorrents/condition/createtime.py
autoremovetorrents/condition/donothing.py
autoremovetorrents/condition/downloaded.py
autoremovetorrents/condition/downloadingtime.py
autoremovetorrents/condition/downloadspeed.py
autoremovetorrents/condition/freespace.py
autoremovetorrents/condition/freespacebase.py
autoremovetorrents/condition/lastactivity.py
autoremovetorrents/condition/leecher.py
autoremovetorrents/condition/progress.py
autoremovetorrents/condition/ratio.py
autoremovetorrents/condition/remotefreespace.py
autoremovetorrents/condition/seeder.py
autoremovetorrents/condition/seedingtime.py
autoremovetorrents/condition/size.py
autoremovetorrents/condition/sortbase.py
autoremovetorrents/condition/torrentnumber.py
autoremovetorrents/condition/torrentsize.py
autoremovetorrents/condition/uploaded.py
autoremove_torrents-1.5.5.dist-info/LICENSE
autoremove_torrents-1.5.5.dist-info/METADATA
autoremove_torrents-1.5.5.dist-info/WHEEL
autoremove_torrents-1.5.5.dist-info/entry_points.txt
autoremove_torrents-1.5.5.dist-info/top_level.txt
autoremove_torrents-1.5.5.dist-info/zip-safe
autoremove_torrents-1.5.5.dist-info/RECORD
