Metadata-Version: 2.1
Name: autoremove-torrents
Version: 1.5.5
Summary: Automatically remove torrents according to your strategies.
Home-page: https://github.com/jerrymakesjelly/autoremove-torrents
Author: jerrymakesjelly
Author-email: ganzhaoyu037@gmail.com
License: MIT
Keywords: python autoremove torrent
Platform: UNKNOWN
Classifier: Environment :: Console
Classifier: License :: OSI Approved :: MIT License
Classifier: Programming Language :: Python
Classifier: Topic :: Utilities
License-File: LICENSE
Requires-Dist: deluge-client
Requires-Dist: enum34
Requires-Dist: ply
Requires-Dist: pyyaml
Requires-Dist: requests
